{
  "id": "set_heating_mode",
  "title": {
    "en": "Set operating mode",
    "nl": "Bedrijfsmodus instellen",
    "de": "Betriebsmodus einstellen",
    "fr": "Régler le mode de fonctionnement"
  },
  "titleFormatted": {
    "en": "Set operating mode to [[mode]]",
    "nl": "Bedrijfsmodus instellen op [[mode]]",
    "de": "Betriebsmodus einstellen auf [[mode]]",
    "fr": "Régler le mode de fonctionnement sur [[mode]]"
  },
  "hint": {
    "en": "Set the operating mode",
    "nl": "Stel de bedrijfsmodus in",
    "de": "Betriebsmodus einstellen",
    "fr": "Régler le mode de fonctionnement"
  },
  "highlight": true,
  "args": [
    {
      "type": "device",
      "name": "device",
      "filter": "driver_id=intelligent-heatpump-modbus"
    },
    {
      "type": "dropdown",
      "name": "mode",
      "title": {
        "en": "Operating mode",
        "nl": "Bedrijfsmodus",
        "de": "Betriebsmodus",
        "fr": "Mode de fonctionnement"
      },
      "values": [
        {
          "id": "cold",
          "title": {
            "en": "Cooling",
            "nl": "Koeling",
            "de": "Kühlung",
            "fr": "Refroidissement"
          }
        },
        {
          "id": "heating",
          "title": {
            "en": "Heating",
            "nl": "Verwarming",
            "de": "Heizung",
            "fr": "Chauffage"
          }
        },
        {
          "id": "floor_heating",
          "title": {
            "en": "Floor heating",
            "nl": "Vloerverwarming",
            "de": "Fußbodenheizung",
            "fr": "Chauffage au sol"
          }
        },
        {
          "id": "hot_water",
          "title": {
            "en": "Hot water",
            "nl": "Warmwater",
            "de": "Warmwasser",
            "fr": "Eau chaude"
          }
        },
        {
          "id": "cold_and_hotwater",
          "title": {
            "en": "Cooling and hot water",
            "nl": "Koeling en warmwater",
            "de": "Kühlung und Warmwasser",
            "fr": "Refroidissement et eau chaude"
          }
        },
        {
          "id": "heating_and_hot_water",
          "title": {
            "en": "Heating and hot water",
            "nl": "Verwarming en warmwater",
            "de": "Heizung und Warmwasser",
            "fr": "Chauffage et eau chaude"
          }
        },
        {
          "id": "floor_heatign_and_hot_water",
          "title": {
            "en": "Floor heating and hot water",
            "nl": "Vloerverwarming en warmwater",
            "de": "Fußbodenheizung und Warmwasser",
            "fr": "Chauffage au sol et eau chaude"
          }
        }
      ]
    }
  ]
}
